_pyattyscomm.cp310-win_amd64.pyd
pyattyscomm.py
pyattyscomm-2.1.1.dist-info/LICENSE
pyattyscomm-2.1.1.dist-info/LICENSE.txt
pyattyscomm-2.1.1.dist-info/METADATA
pyattyscomm-2.1.1.dist-info/WHEEL
pyattyscomm-2.1.1.dist-info/top_level.txt
pyattyscomm-2.1.1.dist-info/RECORD
