Metadata-Version: 2.1
Name: pyattyscomm
Version: 2.1.1
Summary: API for the bluetooth Attys DAQ box (www.attys.tech)
Home-page: https://github.com/glasgowneuro/attys-comm
Author: Bernd Porr
Author-email: bernd@glasgowneuro.tech
License: Apache 2.0
Platform: UNKNOWN
Classifier: Intended Audience :: Developers
Classifier: Operating System :: POSIX
Classifier: Operating System :: Microsoft :: Windows
Classifier: Operating System :: MacOS :: MacOS X
Classifier: Programming Language :: Python
License-File: LICENSE
License-File: LICENSE.txt
